[{"unit": "english", "date": "2017-06-26T06:00:00", "wind_direction": 302.1006595395822, "wind_speed": 11.407931807636931, "wind_gust": 13.422, "wave_summary": {"unit": "english", "wave_height": 2.8535999999999997, "period": 7.54, "direction": 189.37999, "compass_direction": "S", "_max_energy": 0.0, "_frequency_index": 0.0}, "swell_components": [{"unit": "english", "wave_height": 2.7552, "period": 7.39, "direction": 195.70999, "compass_direction": "SSW", "_max_energy": 0.0, "_frequency_index": 0.0}, {"unit": "english", "wave_height": 0.6559999672, "period": 8.36, "direction": 130.41, "compass_direction": "SE", "_max_energy": 0.0, "_frequency_index": 0.0}], "steepness": "", "average_period": null, "wave_spectra": {"frequency": [], "energy": [], "angle": [], "seperation_frequency": null}, "pressure": null, "air_temperature": null, "water_temperature": null, "dewpoint_temperature": null, "pressure_tendency": null, "water_level": null, "energy_spectra_plot": "", "directional_spectra_plot": ""}]